aio_rate_limiter/__init__.py
aio_rate_limiter/aio_rate_limiter.py
aio_rate_limiter-0.1.2.dist-info/LICENSE.md
aio_rate_limiter-0.1.2.dist-info/WHEEL
aio_rate_limiter-0.1.2.dist-info/METADATA
aio_rate_limiter-0.1.2.dist-info/RECORD
