Metadata-Version: 2.1
Name: aio-rate-limiter
Version: 0.1.2
Summary: Rate limit a function using Redis as a backend
License: BSD-3-Clause
Author: Jonathan Drake
Author-email: jdrake@narrativescience.com
Requires-Python: >=3.6,<4.0
Classifier: License :: OSI Approved :: BSD License
Classifier: Programming Language :: Python :: 3
Classifier: Programming Language :: Python :: 3.6
Classifier: Programming Language :: Python :: 3.7
Classifier: Programming Language :: Python :: 3.8
Classifier: Programming Language :: Python :: 3.9
Requires-Dist: aioredis (>=1.3.1,<2.0.0)
